MANIFEST.in
README.md
entrypoints.conf
requirements.txt
setup.py
runlog/VERSION
runlog/__init__.py
runlog/cli.py
runlog/loggage.py
runlog.egg-info/PKG-INFO
runlog.egg-info/SOURCES.txt
runlog.egg-info/dependency_links.txt
runlog.egg-info/entry_points.txt
runlog.egg-info/requires.txt
runlog.egg-info/top_level.txt